niwrap_mrtrix/mrtrix/__init__.py
niwrap_mrtrix/mrtrix/afdconnectivity.py
niwrap_mrtrix/mrtrix/amp2response.py
niwrap_mrtrix/mrtrix/amp2sh.py
niwrap_mrtrix/mrtrix/connectome2tck.py
niwrap_mrtrix/mrtrix/connectomeedit.py
niwrap_mrtrix/mrtrix/connectomestats.py
niwrap_mrtrix/mrtrix/dcmedit.py
niwrap_mrtrix/mrtrix/dcminfo.py
niwrap_mrtrix/mrtrix/dirflip.py
niwrap_mrtrix/mrtrix/dirgen.py
niwrap_mrtrix/mrtrix/dirmerge.py
niwrap_mrtrix/mrtrix/dirorder.py
niwrap_mrtrix/mrtrix/dirsplit.py
niwrap_mrtrix/mrtrix/dirstat.py
niwrap_mrtrix/mrtrix/dwi2adc.py
niwrap_mrtrix/mrtrix/dwi2fod.py
niwrap_mrtrix/mrtrix/dwi2mask.py
niwrap_mrtrix/mrtrix/dwi2response.py
niwrap_mrtrix/mrtrix/dwi2tensor.py
niwrap_mrtrix/mrtrix/dwibiascorrect.py
niwrap_mrtrix/mrtrix/dwidenoise.py
niwrap_mrtrix/mrtrix/dwiextract.py
niwrap_mrtrix/mrtrix/dwigradcheck.py
niwrap_mrtrix/mrtrix/fixel2peaks.py
niwrap_mrtrix/mrtrix/fixel2sh.py
niwrap_mrtrix/mrtrix/fixel2tsf.py
niwrap_mrtrix/mrtrix/fixel2voxel.py
niwrap_mrtrix/mrtrix/fixelcfestats.py
niwrap_mrtrix/mrtrix/fixelconnectivity.py
niwrap_mrtrix/mrtrix/fixelconvert.py
niwrap_mrtrix/mrtrix/fixelcorrespondence.py
niwrap_mrtrix/mrtrix/fixelcrop.py
niwrap_mrtrix/mrtrix/fixelfilter.py
niwrap_mrtrix/mrtrix/fixelreorient.py
niwrap_mrtrix/mrtrix/fod2dec.py
niwrap_mrtrix/mrtrix/fod2fixel.py
niwrap_mrtrix/mrtrix/label2colour.py
niwrap_mrtrix/mrtrix/label2mesh.py
niwrap_mrtrix/mrtrix/labelconvert.py
niwrap_mrtrix/mrtrix/labelstats.py
niwrap_mrtrix/mrtrix/maskdump.py
niwrap_mrtrix/mrtrix/maskfilter.py
niwrap_mrtrix/mrtrix/mesh2voxel.py
niwrap_mrtrix/mrtrix/meshconvert.py
niwrap_mrtrix/mrtrix/meshfilter.py
niwrap_mrtrix/mrtrix/mraverageheader.py
niwrap_mrtrix/mrtrix/mrcalc.py
niwrap_mrtrix/mrtrix/mrcat.py
niwrap_mrtrix/mrtrix/mrcentroid.py
niwrap_mrtrix/mrtrix/mrcheckerboardmask.py
niwrap_mrtrix/mrtrix/mrclusterstats.py
niwrap_mrtrix/mrtrix/mrcolour.py
niwrap_mrtrix/mrtrix/mrconvert.py
niwrap_mrtrix/mrtrix/mrdegibbs.py
niwrap_mrtrix/mrtrix/mrdump.py
niwrap_mrtrix-0.8.3.dist-info/WHEEL
niwrap_mrtrix-0.8.3.dist-info/METADATA
niwrap_mrtrix-0.8.3.dist-info/RECORD
